{
  "name": "Šťastně-podcastový hláškovník",
  "shortName": "stastne-podcastovy_hlaskovnik",
  "description": "Je libo nějaký vtípek?",
  "story": [
    "Text 1, který se mi zatím nechce vytvářet.",
    "Text 2, který taky nevím.",
    "Myslím, že tento hláškovník je opravdu šťastný, protože jste ho právě navštívili."
  ],
  "color": "#BC515A",
  "rootUrl": "sounds/",
  "author": {
    "name": "Honza",
    "url": "https://noURL"
  },
  "lang": "cs",
  "version": "1.0.0",
  "icons": [
    {
      "src": "/icons/og-image.jpg",
      "sizes": "583x330",
      "type": "image/jpeg"
    },
    {
      "src": "/icons/icon-192x192.png",
      "sizes": "192x192",
      "purpose": "192x192",
      "type": "image/png"
    },
    {
      "src": "/icons/icon-512x512.png",
      "sizes": "512x512",
      "type": "image/png"
    }
  ],
  "tiles": [
     {
      "name": "Černochová: Vtípek",
      "filename": "cernochova_vtipek.mp3"
    },
    {
      "name": "Zeman: Fuj",
      "filename": "zeman_fuj.mp3"
    },
    {
      "name": "Zeman: Dobrý!",
      "filename": "zeman_dobry.mp3"
    },
    {
      "name": "Zeman: Chtěl bych vám popřát bolest",
      "filename": "zeman_bolest.mp3"
    },
    {
      "name": "Babiš: Jdeme s trendem",
      "filename": "babis_jdeme_s_trendem.mp3"
    },
    {
      "name": "Babiš: Jsme tady pro vás",
      "filename": "babis_jsme_tady_pro_vas.mp3"
    },
    {
      "name": "Babiš: Moje řeč (2x)",
      "filename": "babis_moje_rec_2x.mp3"
    },
    {
      "name": "Babiš: Koryta (3x)",
      "filename": "babis_koryta_3x.mp3"
    },
    {
      "name": "Babiš: Řekněte přesně, kdo Vám to řek",
      "filename": "babis_reknete_kdo_vam_to_rek.mp3"
    },
    {
      "name": "Babiš: Tak super, takže už to všechno víme",
      "filename": "babis_tak_super_vsechno_vime.mp3"
    },
    {
      "name": "Babiš: Zase jenom kecy v kleci",
      "filename": "babis_zase_jenom_kecy_v_kleci.mp3"
    },
    {
      "name": "Babiš: Totální blackout",
      "filename": "babis_totalni_blackout.mp3"
    },
    {
      "name": "Babiš: Bolela mě normálně hlava asi 3 dny z toho",
      "filename": "babis_bolela_me_hlava_3_dny.mp3"
    },
    {
      "name": "Babiš: Byznys se přizpůsobí",
      "filename": "babis_byznys_se_prizpusobi.mp3"
    },
    {
      "name": "Fiala (ODS): V tomhle já problém nevidím",
      "filename": "fiala_ODS_v_tomhle_ja_problem_nevidim.mp3"
    },
    {
      "name": "Klaus: Nevím (4x)",
      "filename": "klaus_nevim_4x.mp3"
    },
    {
      "name": "Klaus: Tam taky už slaví dneska dopředu, ne?",
      "filename": "klaus_tam_taky_uz_slavi.mp3"
    },
   

    {
      "name": "Nekula (Veselý): Cukr 1",
      "filename": "nekula_vesely_cukr_1.mp3"
    },
    {
      "name": "Nekula (Veselý): Cukr 2",
      "filename": "nekula_vesely_cukr_2.mp3"
    },
    {
      "name": "Nekula (Veselý): U cukru",
      "filename": "nekula_vesely_u_cukru.mp3"
    },
    {
      "name": "Nekula (Veselý): Ať je to třeba cukr",
      "filename": "nekula_vesely_at_je_to_treba_cukr.mp3"
    },
    {
      "name": "Nekula (Veselý): Modelový příklad u cukru",
      "filename": "nekula_vesely_modelovy_priklad_u_cukru.mp3"
    },
    {
      "name": "Nekula (Veselý): A my to vidíme třeba u toho cukru",
      "filename": "nekula_vesely_a_my_to_vidime_u_cukru.mp3"
    },
    {
      "name": "Nekula (Veselý): A zase se chytnu cukru",
      "filename": "nekula_vesely_a_zase_se_chytnu_cukru.mp3"
    },
    {
      "name": "Nekula (Veselý): A cena cukru klesla!",
      "filename": "nekula_vesely_cena_cukru_klesla.mp3"
    }
  ],
  "references": [
    {
      "name": "Hlášky Šťastného podcastu",
      "source": "Seznam Zprávy",
      "url": "https://www.seznamzpravy.cz/sekce/audio-podcast-stastny-podcast-459"
    }
  ],
  "_lyrics": [
    "You ever read the Bible, Brett?",
    "There's a passage I got memorized, seems appropriate for this situation: Ezekiel 25:17.",
    "The path of the righteous man is beset on all sides by the inequities of the selfish and the tyranny of evil men.",
    "Blessed is he who, in the name of charity and good will, shepherds the weak through the valley of darkness, for he is truly his brother's keeper and the finder of lost children.",
    "And I will strike down upon thee with great vengeance and furious anger those who attempt to poison and destroy my brothers.",
    "And you will know my name is the Lord when I lay my vengeance upon you."
  ]
}
